autosegl3/__init__.py
autosegl3/gpu.py
autosegl3/models.py
autosegl3/utils.py
autosegl3/createh5/__init__.py
autosegl3/createh5/createh5.py
autosegl3/genid/__init__.py
autosegl3/genid/genid.py
autosegl3/predict/__init__.py
autosegl3/train/__init__.py
autosegl3/train/train.py
autosegl3-0.11.0.dist-info/AUTHORS.rst
autosegl3-0.11.0.dist-info/METADATA
autosegl3-0.11.0.dist-info/WHEEL
autosegl3-0.11.0.dist-info/entry_points.txt
autosegl3-0.11.0.dist-info/top_level.txt
autosegl3-0.11.0.dist-info/RECORD
