Metadata-Version: 2.1
Name: autosegl3
Version: 0.11.0
Summary: Tool for automatically segmenting muscle and fat tissue in CT images acquired at the
Home-page: https://github.com/rbrecheisen/autosegl3
Author: Ralph Brecheisen
Author-email: ralph.brecheisen@gmail.com
License: UNKNOWN
Keywords: autosegl3
Platform: UNKNOWN
Classifier: Development Status :: 2 - Pre-Alpha
Classifier: Intended Audience :: Developers
Classifier: Natural Language :: English
Classifier: Programming Language :: Python :: 3
Classifier: Programming Language :: Python :: 3.5
Classifier: Programming Language :: Python :: 3.6
Classifier: Programming Language :: Python :: 3.7
Classifier: Programming Language :: Python :: 3.8
Requires-Python: >=3.5
Requires-Dist: barbell2
Requires-Dist: nibabel
Requires-Dist: tensorflow
Requires-Dist: numpy
Requires-Dist: h5py
Requires-Dist: pydicom
